README.md
setup.py
destream/__init__.py
destream/archive.py
destream/guesser.py
destream/helpers.py
destream.egg-info/PKG-INFO
destream.egg-info/SOURCES.txt
destream.egg-info/dependency_links.txt
destream.egg-info/requires.txt
destream.egg-info/top_level.txt
destream/decompressors/__init__.py
destream/decompressors/bzip2.py
destream/decompressors/gzip.py
destream/decompressors/lzma.py
destream/decompressors/p7zip.py
destream/decompressors/rar.py
destream/decompressors/tar.py
destream/decompressors/xz.py
destream/decompressors/zip.py
destream/decompressors/zstd.py
scripts/destream
tests/__init__.py
tests/test_10_base.py
tests/test_30_decompressors.py