Metadata-Version: 1.1
Name: destream
Version: 5.0.1
Summary: A simple module to decompress streams compressed multiple times
Home-page: https://github.com/cecton/destream
Author: Cecile Tonglet
Author-email: cecile.tonglet@cecton.com
License: GPLv2
Keywords: stream file decompress zip zstd
Platform: UNKNOWN
Classifier: Development Status :: 5 - Production/Stable
Classifier: Topic :: System :: Archiving :: Compression
Classifier: License :: OSI Approved :: GNU General Public License v2 (GPLv2)
